youtube_sync/__init__.py
youtube_sync/clean_filename.py
youtube_sync/config.py
youtube_sync/cookies.py
youtube_sync/create.py
youtube_sync/date.py
youtube_sync/fetch_html.py
youtube_sync/ffmpeg.py
youtube_sync/final_result.py
youtube_sync/http_session.py
youtube_sync/integration_test.py
youtube_sync/json_util.py
youtube_sync/library.py
youtube_sync/library_data.py
youtube_sync/logutil.py
youtube_sync/open_webdriver.py
youtube_sync/playwright_launcher.py
youtube_sync/pools.py
youtube_sync/settings.py
youtube_sync/sync.py
youtube_sync/sync_impl.py
youtube_sync/to_channel_url.py
youtube_sync/types.py
youtube_sync/vid_entry.py
youtube_sync/archive/video_info.py
youtube_sync/assets/example.txt
youtube_sync/cli/sync_multiple.py
youtube_sync/cli/sync_one.py
youtube_sync/cli/test_sync_multiple.py
youtube_sync/youtube/bot_scanner.py
youtube_sync/youtube/scan.py
youtube_sync/ytdlp/bulk_download_mp3s.py
youtube_sync/ytdlp/download_best_audio.py
youtube_sync/ytdlp/download_request.py
youtube_sync/ytdlp/download_video_upload_date.py
youtube_sync/ytdlp/downloader.py
youtube_sync/ytdlp/error.py
youtube_sync/ytdlp/exe.py
youtube_sync/ytdlp/exe_result.py
youtube_sync/ytdlp/plugins.py
youtube_sync/ytdlp/scan_for_vids.py
youtube_sync/ytdlp/update.py
youtube_sync/ytdlp/ytdlp.py
youtube_sync-1.2.86.dist-info/licenses/LICENSE
youtube_sync-1.2.86.dist-info/METADATA
youtube_sync-1.2.86.dist-info/WHEEL
youtube_sync-1.2.86.dist-info/entry_points.txt
youtube_sync-1.2.86.dist-info/top_level.txt
youtube_sync-1.2.86.dist-info/RECORD
