Metadata-Version: 2.4
Name: youtube_sync
Version: 1.2.86
Summary: syncs youtube for offline play
Home-page: https://github.com/zackees/youtube-sync
Maintainer: Zachary Vorhies
License-Expression: BSD-3-Clause
Keywords: template-python-cmd
Classifier: Programming Language :: Python :: 3
Requires-Python: >=3.10
License-File: LICENSE
Requires-Dist: filelock
Requires-Dist: ytdlp-brighteon>=2023.10.3
Requires-Dist: docker-run-cmd>=1.0.13
Requires-Dist: Pillow
Requires-Dist: certifi
Requires-Dist: appdirs
Requires-Dist: open-webdriver>=1.6.9
Requires-Dist: pytz
Requires-Dist: python-dateutil
Requires-Dist: feedparser
Requires-Dist: download
Requires-Dist: static-ffmpeg>=2.12
Requires-Dist: pytest-playwright
Requires-Dist: beautifulsoup4>=4.13.3
Requires-Dist: virtual-fs>=1.0.24
Requires-Dist: webdriver-manager
Requires-Dist: pyvirtualdisplay
Requires-Dist: yt-dlp[curl-cffi,default]>=2025.3.31
Requires-Dist: rclone-api>=1.5.61
Requires-Dist: yt-dlp-proxy>=1.0.7
Requires-Dist: youtube-trusted-session-generator>=0.0.4
Requires-Dist: yt-dlp-get-pot
Dynamic: home-page
Dynamic: license-file
